spotify_preview_finder/__init__.py
spotify_preview_finder/finder.py
spotify_preview_finder-1.2.0.dist-info/licenses/LICENSE
spotify_preview_finder-1.2.0.dist-info/METADATA
spotify_preview_finder-1.2.0.dist-info/WHEEL
spotify_preview_finder-1.2.0.dist-info/top_level.txt
spotify_preview_finder-1.2.0.dist-info/RECORD
